AUTHORS
Announce
COPYING
INSTALL
MANIFEST.in
README
README.localization
changelog
setup.cfg
setup.py
sqledit.completion
sqlkit.desktop
demo/__init__.py
demo/demo_tour.py
demo/layout/00_alignment.py
demo/layout/00_button.py
demo/layout/00_check.py
demo/layout/00_combobox.py
demo/layout/00_connect.py
demo/layout/00_date.py
demo/layout/00_entry.py
demo/layout/00_event.py
demo/layout/00_frame.py
demo/layout/00_handle.py
demo/layout/00_img.py
demo/layout/00_label.py
demo/layout/00_layout.py
demo/layout/00_spin.py
demo/layout/00_tips.py
demo/layout/00_tool_calendar.py
demo/layout/00_toolbar.py
demo/layout/00_translation.py
demo/layout/01_connect.py
demo/layout/01_toolbar.py
demo/layout/50_entry_menu.py
demo/layout/50_eurotex.py
demo/layout/50_expand_toggle_combo.py
demo/layout/50_notebook_client.py
demo/layout/50_scrolled.py
demo/layout/demo.py
demo/layout/frame_compact.py
demo/layout/frame_long.py
demo/layout/notebook_menu_paned.py
demo/sql/demo.py
demo/sql/ex_01_table_movie.py
demo/sql/ex_02_mask_movie.py
demo/sql/ex_02a_table_movie.py
demo/sql/ex_02b_mask_movie.py
demo/sql/ex_03_table_totals.py
demo/sql/ex_04_table_filter.py
demo/sql/ex_05_constraints.py
demo/sql/ex_06_table_filter.py
demo/sql/ex_07_date_relative.py
demo/sql/ex_08_table_noup.py
demo/sql/ex_09_table_hide.py
demo/sql/ex_10_opts_dev.py
demo/sql/ex_11_opts_mode.py
demo/sql/ex_12_opts_geom.py
demo/sql/ex_13_opts_rows.py
demo/sql/ex_13b_opts_format.py
demo/sql/ex_13c_opts_order_by.py
demo/sql/ex_14_default.py
demo/sql/ex_15_base_all_types.py
demo/sql/ex_15b_base_all_types.py
demo/sql/ex_16_join.py
demo/sql/ex_17_hard_way.py
demo/sql/ex_18_record_in_mask.py
demo/sql/ex_20_relations_movie.py
demo/sql/ex_20b_adding_records.py
demo/sql/ex_21_relations_select_fields.py
demo/sql/ex_22_relations_filter_join.py
demo/sql/ex_23_relations_filter_join.py
demo/sql/ex_25_relations_m2m.py
demo/sql/ex_26_relations_m2m_table.py
demo/sql/ex_27_relations_m2m_editable.py
demo/sql/ex_30_mapper_count.py
sqlkit.egg-info/PKG-INFO
sqlkit.egg-info/SOURCES.txt
sqlkit.egg-info/dependency_links.txt
sqlkit.egg-info/entry_points.txt
sqlkit.egg-info/not-zip-safe
sqlkit.egg-info/top_level.txt
