Metadata-Version: 1.1
Name: sqlkit
Version: 0.9.6
Summary: GUI to edit databases. Many backend supported (Postgres, Sqlite, MySql,...).
